cuequivariance_ops/VERSION
cuequivariance_ops/__init__.py
cuequivariance_ops/_version.py
cuequivariance_ops/gpu_timing_kernels.hh
cuequivariance_ops/sleep.hh
cuequivariance_ops/common/common.hpp
cuequivariance_ops/common/cudart.hpp
cuequivariance_ops/common/error.hpp
cuequivariance_ops/common/error_raft.hpp
cuequivariance_ops/common/nvtx.hpp
cuequivariance_ops/equivariance/batch_dimension.hh
cuequivariance_ops/equivariance/dtypes.hh
cuequivariance_ops/equivariance/fused_tensor_product.cuh
cuequivariance_ops/equivariance/indexed_linear.hh
cuequivariance_ops/equivariance/run_fmha.h
cuequivariance_ops/equivariance/run_fmha_cudafree.h
cuequivariance_ops/equivariance/run_fmha_sm100.h
cuequivariance_ops/equivariance/segmented_transpose.cuh
cuequivariance_ops/equivariance/tensor_product_uniform_1d_jit.hh
cuequivariance_ops/lib/libcue_ops.so
cuequivariance_ops/triton/__init__.py
cuequivariance_ops/triton/cache_manager.py
cuequivariance_ops/triton/fused_layer_norm_triton.py
cuequivariance_ops/triton/gated_gemm_triton.py
cuequivariance_ops/triton/pair_bias.py
cuequivariance_ops/triton/tuning_decorator.py
cuequivariance_ops/triton/utils.py
cuequivariance_ops/triton/cache/fused_sigmoid_gated_dual_gemm_backward_pregemm_kernel_wrapper.10.0.json
cuequivariance_ops/triton/cache/fused_sigmoid_gated_dual_gemm_backward_pregemm_kernel_wrapper.12.0.json
cuequivariance_ops/triton/cache/fused_sigmoid_gated_dual_gemm_backward_pregemm_kernel_wrapper.8.0.json
cuequivariance_ops/triton/cache/fused_sigmoid_gated_dual_gemm_backward_pregemm_kernel_wrapper.8.6.json
cuequivariance_ops/triton/cache/fused_sigmoid_gated_dual_gemm_backward_pregemm_kernel_wrapper.8.9.json
cuequivariance_ops/triton/cache/fused_sigmoid_gated_dual_gemm_backward_pregemm_kernel_wrapper.9.0.json
cuequivariance_ops/triton/cache/fused_sigmoid_gated_dual_gemm_forward_kernel_wrapper.10.0.json
cuequivariance_ops/triton/cache/fused_sigmoid_gated_dual_gemm_forward_kernel_wrapper.12.0.json
cuequivariance_ops_cu13-0.8.1.dist-info/METADATA
cuequivariance_ops_cu13-0.8.1.dist-info/WHEEL
cuequivariance_ops_cu13-0.8.1.dist-info/RECORD
cuequivariance_ops_cu13-0.8.1.dist-info/licenses/LICENSE
cuequivariance_ops_cu13-0.8.1.dist-info/licenses/Third_party_attr.txt
cuequivariance_ops_cu13-0.8.1.dist-info/sboms/auditwheel.cdx.json
