Metadata-Version: 2.2
Name: cuequivariance-ops-cu13
Version: 0.8.1
Summary: cuequivariance-ops - GPU Accelerated Extensions for Equivariant Primitives
Author: NVIDIA Corporation
License: # Software License Agreement
Classifier: Intended Audience :: Developers
Classifier: Programming Language :: Python
Project-URL: Homepage, https://github.com/nvidia/cuEquivariance
Project-URL: Documentation, https://github.com/nvidia/cuEquivariance
Requires-Python: >=3.10
Requires-Dist: nvidia-cublas>=12.5.0
Requires-Dist: tqdm
Requires-Dist: nvidia-ml-py
Requires-Dist: platformdirs
Provides-Extra: test
Requires-Dist: numpy; extra == "test"
Requires-Dist: pytest; extra == "test"
